{
    "commodities": [
        {
            "EAT": "2017-05-16 08:15:00",
            "LDT": "2017-05-17 20:15:00",
            "source": "Berth 33A",
            "name": "AS FIORELLA",
            "commodityGroup": "Paper",
            "destination": "FL",
            "origin": "BRAZIL",
            "nTEU": 34.0,
            "group_uuid": "3ec53af4-d50b-466a-ac3e-9c7e17249900",
            "cargo_categories": [
                "Non-hazardous"
            ],
            "delay_cost": null,
            "transportation_methods": [
                "Roadway",
                "Sea",
                "Transloading"
            ]
        },
        {
            "EAT": "2017-05-16 08:15:00",
            "LDT": "2017-05-17 20:15:00",
            "source": "Berth 33A",
            "name": "AS FIORELLA",
            "commodityGroup": "Home Furnishings & Accessories (excl. Furniture)",
            "destination": "NY",
            "origin": "ITALY",
            "nTEU": 4.0,
            "group_uuid": "328a8a98-9380-482c-84a0-2c617d576129",
            "cargo_categories": [
                "Non-hazardous"
            ],
            "delay_cost": null,
            "transportation_methods": [
                "Roadway",
                "Sea",
                "Transloading"
            ]
        },
        {
            "EAT": "2017-05-16 08:15:00",
            "LDT": "2017-05-17 20:15:00",
            "source": "Berth 33A",
            "name": "AS FIORELLA",
            "commodityGroup": "Lumber",
            "destination": "FL",
            "origin": "BRAZIL",
            "nTEU": 6.0,
            "group_uuid": "ec2a205c-ff9b-4405-a895-71fc44562071",
            "cargo_categories": [
                "Non-hazardous"
            ],
            "delay_cost": null,
            "transportation_methods": [
                "Roadway",
                "Sea",
                "Transloading"
            ]
        },
        {
            "EAT": "2017-05-16 08:15:00",
            "LDT": "2017-05-17 20:15:00",
            "source": "Berth 33A",
            "name": "AS FIORELLA",
            "commodityGroup": "Machinery",
            "destination": "FL",
            "origin": "TURKS AND CAICOS IS",
            "nTEU": 0.0,
            "group_uuid": "5aaf1b99-c5df-4229-9cd0-8e2b8411c655",
            "cargo_categories": [
                "Non-hazardous"
            ],
            "delay_cost": null,
            "transportation_methods": [
                "Roadway",
                "Sea",
                "Transloading"
            ]
        },
        {
            "EAT": "2017-05-16 08:15:00",
            "LDT": "2017-05-17 20:15:00",
            "source": "Berth 33A",
            "name": "AS FIORELLA",
            "commodityGroup": "Beverages",
            "destination": "NY",
            "origin": "ITALY",
            "nTEU": 13.15,
            "group_uuid": "7060a037-0629-4ff5-be29-972871313562",
            "cargo_categories": [
                "Non-hazardous"
            ],
            "delay_cost": null,
            "transportation_methods": [
                "Roadway",
                "Sea",
                "Transloading"
            ]
        },
        {
            "EAT": "2017-05-16 08:15:00",
            "LDT": "2017-05-17 20:15:00",
            "source": "Berth 33A",
            "name": "AS FIORELLA",
            "commodityGroup": "Vehicle Parts",
            "destination": "MI",
            "origin": "HONDURAS",
            "nTEU": 1.52,
            "group_uuid": "f1a5c6c0-9955-4304-b8ec-e1b39486a415",
            "cargo_categories": [
                "Non-hazardous"
            ],
            "delay_cost": null,
            "transportation_methods": [
                "Roadway",
                "Sea",
                "Transloading"
            ]
        },
        {
            "EAT": "2017-05-16 08:15:00",
            "LDT": "2017-05-17 20:15:00",
            "source": "Berth 33A",
            "name": "AS FIORELLA",
            "commodityGroup": "Steel Products",
            "destination": "FL",
            "origin": "DOMINICAN REPUBLIC",
            "nTEU": 3.0,
            "group_uuid": "bb57fcef-f14c-4840-8bf7-f791f858cfea",
            "cargo_categories": [
                "Non-hazardous"
            ],
            "delay_cost": null,
            "transportation_methods": [
                "Roadway",
                "Sea",
                "Transloading"
            ]
        },
        {
            "EAT": "2017-05-16 08:15:00",
            "LDT": "2017-05-17 20:15:00",
            "source": "Berth 33A",
            "name": "AS FIORELLA",
            "commodityGroup": "All Others",
            "destination": "CA",
            "origin": "GUATEMALA",
            "nTEU": 29.92,
            "group_uuid": "cc6c9eaf-eecf-4073-96b9-c1bf581337e9",
            "cargo_categories": [
                "Non-hazardous"
            ],
            "delay_cost": null,
            "transportation_methods": [
                "Roadway",
                "Sea",
                "Transloading"
            ]
        },
        {
            "EAT": "2017-05-16 08:15:00",
            "LDT": "2017-05-17 20:15:00",
            "source": "Berth 33A",
            "name": "AS FIORELLA",
            "commodityGroup": "Machinery",
            "destination": "SC",
            "origin": "HONDURAS",
            "nTEU": 2.0,
            "group_uuid": "374c9832-804e-4802-85e6-728a603f8270",
            "cargo_categories": [
                "Non-hazardous"
            ],
            "delay_cost": null,
            "transportation_methods": [
                "Roadway",
                "Sea",
                "Transloading"
            ]
        },
        {
            "EAT": "2017-05-16 08:15:00",
            "LDT": "2017-05-17 20:15:00",
            "source": "Berth 33A",
            "name": "AS FIORELLA",
            "commodityGroup": "Government",
            "destination": "FL",
            "origin": "JAMAICA",
            "nTEU": 10.0,
            "group_uuid": "4ae2ca58-8639-435a-8c41-74e7ddc1473b",
            "cargo_categories": [
                "Non-hazardous"
            ],
            "delay_cost": null,
            "transportation_methods": [
                "Roadway",
                "Sea",
                "Transloading"
            ]
        },
        {
            "EAT": "2017-05-16 08:15:00",
            "LDT": "2017-05-17 20:15:00",
            "source": "Berth 33A",
            "name": "AS FIORELLA",
            "commodityGroup": "Other Food Products",
            "destination": "FL",
            "origin": "SPAIN-S",
            "nTEU": 5.75,
            "group_uuid": "1ccf853b-cbba-4f3c-a2fe-b58943fa4065",
            "cargo_categories": [
                "Non-hazardous"
            ],
            "delay_cost": null,
            "transportation_methods": [
                "Roadway",
                "Sea",
                "Transloading"
            ]
        },
        {
            "EAT": "2017-05-16 08:15:00",
            "LDT": "2017-05-17 20:15:00",
            "source": "Berth 33A",
            "name": "AS FIORELLA",
            "commodityGroup": "Rubber",
            "destination": "CA",
            "origin": "ITALY",
            "nTEU": 2.0,
            "group_uuid": "c6f63b53-b631-415d-8edc-2c6accb9d57f",
            "cargo_categories": [
                "Non-hazardous"
            ],
            "delay_cost": null,
            "transportation_methods": [
                "Roadway",
                "Sea",
                "Transloading"
            ]
        },
        {
            "EAT": "2017-05-16 08:15:00",
            "LDT": "2017-05-17 20:15:00",
            "source": "Berth 33A",
            "name": "AS FIORELLA",
            "commodityGroup": "Motor Vehicles",
            "destination": "FL",
            "origin": "VIRGIN ISLAND",
            "nTEU": 2.0,
            "group_uuid": "6742c8a6-c139-4c66-b698-cfd0c4bb0d11",
            "cargo_categories": [
                "Non-hazardous"
            ],
            "delay_cost": null,
            "transportation_methods": [
                "Roadway",
                "Sea",
                "Transloading"
            ]
        },
        {
            "EAT": "2017-05-16 08:15:00",
            "LDT": "2017-05-17 20:15:00",
            "source": "Berth 33A",
            "name": "AS FIORELLA",
            "commodityGroup": "Waste Products",
            "destination": "FL",
            "origin": "DOMINICAN REPUBLIC",
            "nTEU": 1.91,
            "group_uuid": "7cd06878-5ace-4fbb-9c68-6944f32d4555",
            "cargo_categories": [
                "Non-hazardous"
            ],
            "delay_cost": null,
            "transportation_methods": [
                "Roadway",
                "Sea",
                "Transloading"
            ]
        },
        {
            "EAT": "2017-05-16 08:15:00",
            "LDT": "2017-05-17 20:15:00",
            "source": "Berth 33A",
            "name": "AS FIORELLA",
            "commodityGroup": "Oils",
            "destination": "FL",
            "origin": "ITALY",
            "nTEU": 2.0,
            "group_uuid": "3165290c-e573-4358-9ea4-5584b06559da",
            "cargo_categories": [
                "Non-hazardous"
            ],
            "delay_cost": null,
            "transportation_methods": [
                "Roadway",
                "Sea",
                "Transloading"
            ]
        },
        {
            "EAT": "2017-05-16 08:15:00",
            "LDT": "2017-05-17 20:15:00",
            "source": "Berth 33A",
            "name": "AS FIORELLA",
            "commodityGroup": "Sporting Goods",
            "destination": "FL",
            "origin": "ITALY",
            "nTEU": 2.0,
            "group_uuid": "63bf8ac1-9e2e-40db-8d5e-46fbbfeceb27",
            "cargo_categories": [
                "Non-hazardous"
            ],
            "delay_cost": null,
            "transportation_methods": [
                "Roadway",
                "Sea",
                "Transloading"
            ]
        }
    ]
}