{
    "commodities": [
        {
            "EAT": "2017-05-16 05:45:00",
            "LDT": "2017-05-17 17:45:00",
            "source": "Berth 32",
            "name": "MSC FLORENTINA",
            "commodityGroup": "Lumber",
            "destination": "FL",
            "origin": "COLOMBIA",
            "nTEU": 85.07,
            "group_uuid": "8d3e56f0-8565-446b-979e-22d4f3e8872e",
            "cargo_categories": [
                "Non-hazardous"
            ],
            "delay_cost": null,
            "transportation_methods": [
                "Roadway",
                "Sea",
                "Transloading"
            ]
        },
        {
            "EAT": "2017-05-16 05:45:00",
            "LDT": "2017-05-17 17:45:00",
            "source": "Berth 32",
            "name": "MSC FLORENTINA",
            "commodityGroup": "Toys",
            "destination": "FL",
            "origin": "BAHAMAS",
            "nTEU": 7.05,
            "group_uuid": "c89b3312-b2ca-43ed-960d-bb57b1c9e305",
            "cargo_categories": [
                "Non-hazardous"
            ],
            "delay_cost": null,
            "transportation_methods": [
                "Roadway",
                "Sea",
                "Transloading"
            ]
        },
        {
            "EAT": "2017-05-16 05:45:00",
            "LDT": "2017-05-17 17:45:00",
            "source": "Berth 32",
            "name": "MSC FLORENTINA",
            "commodityGroup": "Textiles",
            "destination": "MD",
            "origin": "HONDURAS",
            "nTEU": 1.82,
            "group_uuid": "e22b2b6a-e302-40a0-8ff3-98fe31f919c1",
            "cargo_categories": [
                "Non-hazardous"
            ],
            "delay_cost": null,
            "transportation_methods": [
                "Roadway",
                "Sea",
                "Transloading"
            ]
        },
        {
            "EAT": "2017-05-16 05:45:00",
            "LDT": "2017-05-17 17:45:00",
            "source": "Berth 32",
            "name": "MSC FLORENTINA",
            "commodityGroup": "Aggregates",
            "destination": "FL",
            "origin": "BRAZIL",
            "nTEU": 70.24,
            "group_uuid": "ff6ff073-03be-4d48-875c-b54f3c0cad9f",
            "cargo_categories": [
                "Non-hazardous"
            ],
            "delay_cost": null,
            "transportation_methods": [
                "Roadway",
                "Sea",
                "Transloading"
            ]
        },
        {
            "EAT": "2017-05-16 05:45:00",
            "LDT": "2017-05-17 17:45:00",
            "source": "Berth 32",
            "name": "MSC FLORENTINA",
            "commodityGroup": "All Others",
            "destination": "FL",
            "origin": "GUATEMALA",
            "nTEU": 0.95,
            "group_uuid": "9fc97cc9-857e-4ddd-8680-14b1b1d581b3",
            "cargo_categories": [
                "Non-hazardous"
            ],
            "delay_cost": null,
            "transportation_methods": [
                "Roadway",
                "Sea",
                "Transloading"
            ]
        },
        {
            "EAT": "2017-05-16 05:45:00",
            "LDT": "2017-05-17 17:45:00",
            "source": "Berth 32",
            "name": "MSC FLORENTINA",
            "commodityGroup": "Furniture",
            "destination": "FL",
            "origin": "ITALY",
            "nTEU": 2.01,
            "group_uuid": "235fe583-2070-4e32-a8a4-f0ef7e833429",
            "cargo_categories": [
                "Non-hazardous"
            ],
            "delay_cost": null,
            "transportation_methods": [
                "Roadway",
                "Sea",
                "Transloading"
            ]
        },
        {
            "EAT": "2017-05-16 05:45:00",
            "LDT": "2017-05-17 17:45:00",
            "source": "Berth 32",
            "name": "MSC FLORENTINA",
            "commodityGroup": "Furniture",
            "destination": "FL",
            "origin": "ITALY",
            "nTEU": 8.25,
            "group_uuid": "ac2ad41c-6d8f-4423-a8cd-3ea34c3122f8",
            "cargo_categories": [
                "Non-hazardous"
            ],
            "delay_cost": null,
            "transportation_methods": [
                "Roadway",
                "Sea",
                "Transloading"
            ]
        },
        {
            "EAT": "2017-05-16 05:45:00",
            "LDT": "2017-05-17 17:45:00",
            "source": "Berth 32",
            "name": "MSC FLORENTINA",
            "commodityGroup": "Beverages",
            "destination": "MN",
            "origin": "COLOMBIA",
            "nTEU": 5.75,
            "group_uuid": "3774c413-fcab-4564-ac08-27c657214218",
            "cargo_categories": [
                "Non-hazardous"
            ],
            "delay_cost": null,
            "transportation_methods": [
                "Roadway",
                "Sea",
                "Transloading"
            ]
        },
        {
            "EAT": "2017-05-16 05:45:00",
            "LDT": "2017-05-17 17:45:00",
            "source": "Berth 32",
            "name": "MSC FLORENTINA",
            "commodityGroup": "Footwear",
            "destination": "MI",
            "origin": "DOMINICAN REPUBLIC",
            "nTEU": 1.0,
            "group_uuid": "6759af5b-95ca-478d-87e8-786ee8feb257",
            "cargo_categories": [
                "Non-hazardous"
            ],
            "delay_cost": null,
            "transportation_methods": [
                "Roadway",
                "Sea",
                "Transloading"
            ]
        },
        {
            "EAT": "2017-05-16 05:45:00",
            "LDT": "2017-05-17 17:45:00",
            "source": "Berth 32",
            "name": "MSC FLORENTINA",
            "commodityGroup": "Panel Products",
            "destination": "FL",
            "origin": "ECUADOR",
            "nTEU": 14.83,
            "group_uuid": "983eb726-61af-4ac7-88d9-07499c54bf7b",
            "cargo_categories": [
                "Non-hazardous"
            ],
            "delay_cost": null,
            "transportation_methods": [
                "Roadway",
                "Sea",
                "Transloading"
            ]
        },
        {
            "EAT": "2017-05-16 05:45:00",
            "LDT": "2017-05-17 17:45:00",
            "source": "Berth 32",
            "name": "MSC FLORENTINA",
            "commodityGroup": "Electronics/Instruments",
            "destination": "TN",
            "origin": "DOMINICAN REPUBLIC",
            "nTEU": 1.75,
            "group_uuid": "19a75baa-dfde-4652-a8e1-4bf86926718f",
            "cargo_categories": [
                "Non-hazardous"
            ],
            "delay_cost": null,
            "transportation_methods": [
                "Roadway",
                "Sea",
                "Transloading"
            ]
        },
        {
            "EAT": "2017-05-16 05:45:00",
            "LDT": "2017-05-17 17:45:00",
            "source": "Berth 32",
            "name": "MSC FLORENTINA",
            "commodityGroup": "Fruits and Vegetables",
            "destination": "FL",
            "origin": "HONDURAS",
            "nTEU": 2.0,
            "group_uuid": "3f8ec618-977d-4aa8-9b63-5b9735b5f5c0",
            "cargo_categories": [
                "Non-hazardous"
            ],
            "delay_cost": null,
            "transportation_methods": [
                "Roadway",
                "Sea",
                "Transloading"
            ]
        },
        {
            "EAT": "2017-05-16 05:45:00",
            "LDT": "2017-05-17 17:45:00",
            "source": "Berth 32",
            "name": "MSC FLORENTINA",
            "commodityGroup": "Paper",
            "destination": "FL",
            "origin": "BRAZIL",
            "nTEU": 184.01,
            "group_uuid": "24885627-afe7-445b-87ea-419c8388e819",
            "cargo_categories": [
                "Non-hazardous"
            ],
            "delay_cost": null,
            "transportation_methods": [
                "Roadway",
                "Sea",
                "Transloading"
            ]
        },
        {
            "EAT": "2017-05-16 05:45:00",
            "LDT": "2017-05-17 17:45:00",
            "source": "Berth 32",
            "name": "MSC FLORENTINA",
            "commodityGroup": "All Others",
            "destination": "FL",
            "origin": "GUATEMALA",
            "nTEU": 19.32,
            "group_uuid": "b54aef81-c49a-4ef1-8348-993a3e2ae121",
            "cargo_categories": [
                "Non-hazardous"
            ],
            "delay_cost": null,
            "transportation_methods": [
                "Roadway",
                "Sea",
                "Transloading"
            ]
        },
        {
            "EAT": "2017-05-16 05:45:00",
            "LDT": "2017-05-17 17:45:00",
            "source": "Berth 32",
            "name": "MSC FLORENTINA",
            "commodityGroup": "Other Manufactured Plastic Products",
            "destination": "FL",
            "origin": "COLOMBIA",
            "nTEU": 5.59,
            "group_uuid": "82dfd1d3-95b3-4a35-835d-7b2668a29e1f",
            "cargo_categories": [
                "Non-hazardous"
            ],
            "delay_cost": null,
            "transportation_methods": [
                "Roadway",
                "Sea",
                "Transloading"
            ]
        },
        {
            "EAT": "2017-05-16 05:45:00",
            "LDT": "2017-05-17 17:45:00",
            "source": "Berth 32",
            "name": "MSC FLORENTINA",
            "commodityGroup": "Corn",
            "destination": "FL",
            "origin": "COLOMBIA",
            "nTEU": 0.01,
            "group_uuid": "ba8b3c36-aee6-4026-b30b-4cd8ba218105",
            "cargo_categories": [
                "Non-hazardous"
            ],
            "delay_cost": null,
            "transportation_methods": [
                "Roadway",
                "Sea",
                "Transloading"
            ]
        },
        {
            "EAT": "2017-05-16 05:45:00",
            "LDT": "2017-05-17 17:45:00",
            "source": "Berth 32",
            "name": "MSC FLORENTINA",
            "commodityGroup": "Sporting Goods",
            "destination": "GA",
            "origin": "BRAZIL",
            "nTEU": 1.0,
            "group_uuid": "b9b65549-0e88-498d-83f0-253516af30e2",
            "cargo_categories": [
                "Non-hazardous"
            ],
            "delay_cost": null,
            "transportation_methods": [
                "Roadway",
                "Sea",
                "Transloading"
            ]
        },
        {
            "EAT": "2017-05-16 05:45:00",
            "LDT": "2017-05-17 17:45:00",
            "source": "Berth 32",
            "name": "MSC FLORENTINA",
            "commodityGroup": "Bulk Foods",
            "destination": "FL",
            "origin": "PANAMA",
            "nTEU": 12.0,
            "group_uuid": "1d4bf367-3354-4343-842f-44b54c9139fa",
            "cargo_categories": [
                "Non-hazardous"
            ],
            "delay_cost": null,
            "transportation_methods": [
                "Roadway",
                "Sea",
                "Transloading"
            ]
        },
        {
            "EAT": "2017-05-16 05:45:00",
            "LDT": "2017-05-17 17:45:00",
            "source": "Berth 32",
            "name": "MSC FLORENTINA",
            "commodityGroup": "Industrial Chemicals",
            "destination": "FL",
            "origin": "ITALY",
            "nTEU": 1.02,
            "group_uuid": "8bca4217-3780-48fe-8766-cc5aa1e768cf",
            "cargo_categories": [
                "Non-hazardous"
            ],
            "delay_cost": null,
            "transportation_methods": [
                "Roadway",
                "Sea",
                "Transloading"
            ]
        },
        {
            "EAT": "2017-05-16 05:45:00",
            "LDT": "2017-05-17 17:45:00",
            "source": "Berth 32",
            "name": "MSC FLORENTINA",
            "commodityGroup": "Petroleum Products",
            "destination": "FL",
            "origin": "TURKS AND CAICOS IS",
            "nTEU": 1.0,
            "group_uuid": "99cbd212-42e4-4da5-8fa2-3f18486273cf",
            "cargo_categories": [
                "Non-hazardous"
            ],
            "delay_cost": null,
            "transportation_methods": [
                "Roadway",
                "Sea",
                "Transloading"
            ]
        },
        {
            "EAT": "2017-05-16 05:45:00",
            "LDT": "2017-05-17 17:45:00",
            "source": "Berth 32",
            "name": "MSC FLORENTINA",
            "commodityGroup": "Specialty Grains",
            "destination": "FL",
            "origin": "PANAMA",
            "nTEU": 9.0,
            "group_uuid": "42912c2f-d044-4902-a7cc-6b2a53b63500",
            "cargo_categories": [
                "Non-hazardous"
            ],
            "delay_cost": null,
            "transportation_methods": [
                "Roadway",
                "Sea",
                "Transloading"
            ]
        },
        {
            "EAT": "2017-05-16 05:45:00",
            "LDT": "2017-05-17 17:45:00",
            "source": "Berth 32",
            "name": "MSC FLORENTINA",
            "commodityGroup": "Glass/Ceramic",
            "destination": "FL",
            "origin": "PORTUGAL",
            "nTEU": 4.75,
            "group_uuid": "b7929416-12ff-4c3c-a47f-30f214a03f9c",
            "cargo_categories": [
                "Non-hazardous"
            ],
            "delay_cost": null,
            "transportation_methods": [
                "Roadway",
                "Sea",
                "Transloading"
            ]
        },
        {
            "EAT": "2017-05-16 05:45:00",
            "LDT": "2017-05-17 17:45:00",
            "source": "Berth 32",
            "name": "MSC FLORENTINA",
            "commodityGroup": "Glass/Ceramic",
            "destination": "FL",
            "origin": "BRAZIL",
            "nTEU": 5.41,
            "group_uuid": "35722e4f-39c1-48fe-9773-d1182fd8119c",
            "cargo_categories": [
                "Non-hazardous"
            ],
            "delay_cost": null,
            "transportation_methods": [
                "Roadway",
                "Sea",
                "Transloading"
            ]
        },
        {
            "EAT": "2017-05-16 05:45:00",
            "LDT": "2017-05-17 17:45:00",
            "source": "Berth 32",
            "name": "MSC FLORENTINA",
            "commodityGroup": "Machinery",
            "destination": "FL",
            "origin": "SURINAM",
            "nTEU": 2.18,
            "group_uuid": "449665fe-c185-43d7-88d6-f1f33016793f",
            "cargo_categories": [
                "Non-hazardous"
            ],
            "delay_cost": null,
            "transportation_methods": [
                "Roadway",
                "Sea",
                "Transloading"
            ]
        },
        {
            "EAT": "2017-05-16 05:45:00",
            "LDT": "2017-05-17 17:45:00",
            "source": "Berth 32",
            "name": "MSC FLORENTINA",
            "commodityGroup": "Soybeans",
            "destination": "IN",
            "origin": "URUGUAY",
            "nTEU": 26.0,
            "group_uuid": "b07dbcfe-1a6b-4597-9eb3-70f0050d6523",
            "cargo_categories": [
                "Non-hazardous"
            ],
            "delay_cost": null,
            "transportation_methods": [
                "Roadway",
                "Sea",
                "Transloading"
            ]
        }
    ]
}