{
    "commodities": [
        {
            "EAT": "2017-05-09 06:35:00",
            "LDT": "2017-05-10 18:35:00",
            "source": "Berth 32",
            "name": "MSC MARINA",
            "commodityGroup": "Fruits and Vegetables",
            "destination": "FL",
            "origin": "GUATEMALA",
            "nTEU": 6.0,
            "group_uuid": "5308c9a0-5e5f-4242-9ebd-3416e169928d",
            "cargo_categories": [
                "Non-hazardous"
            ],
            "delay_cost": null,
            "transportation_methods": [
                "Roadway",
                "Sea",
                "Transloading"
            ]
        },
        {
            "EAT": "2017-05-09 06:35:00",
            "LDT": "2017-05-10 18:35:00",
            "source": "Berth 32",
            "name": "MSC MARINA",
            "commodityGroup": "Home Furnishings & Accessories (excl. Furniture)",
            "destination": "FL",
            "origin": "COLOMBIA",
            "nTEU": 5.51,
            "group_uuid": "68c74f42-b23d-434e-bb1c-4c820f4d9652",
            "cargo_categories": [
                "Non-hazardous"
            ],
            "delay_cost": null,
            "transportation_methods": [
                "Roadway",
                "Sea",
                "Transloading"
            ]
        },
        {
            "EAT": "2017-05-09 06:35:00",
            "LDT": "2017-05-10 18:35:00",
            "source": "Berth 32",
            "name": "MSC MARINA",
            "commodityGroup": "Footwear",
            "destination": "FL",
            "origin": "ITALY",
            "nTEU": 2.0,
            "group_uuid": "5130ab33-81fb-43a3-a64d-ff0356a58ab8",
            "cargo_categories": [
                "Non-hazardous"
            ],
            "delay_cost": null,
            "transportation_methods": [
                "Roadway",
                "Sea",
                "Transloading"
            ]
        },
        {
            "EAT": "2017-05-09 06:35:00",
            "LDT": "2017-05-10 18:35:00",
            "source": "Berth 32",
            "name": "MSC MARINA",
            "commodityGroup": "Lumber",
            "destination": "MI",
            "origin": "JAMAICA",
            "nTEU": 90.92,
            "group_uuid": "479381db-f251-4722-89cc-4136ec936d1a",
            "cargo_categories": [
                "Non-hazardous"
            ],
            "delay_cost": null,
            "transportation_methods": [
                "Roadway",
                "Sea",
                "Transloading"
            ]
        },
        {
            "EAT": "2017-05-09 06:35:00",
            "LDT": "2017-05-10 18:35:00",
            "source": "Berth 32",
            "name": "MSC MARINA",
            "commodityGroup": "Paper",
            "destination": "FL",
            "origin": "BRAZIL",
            "nTEU": 45.5,
            "group_uuid": "9af2ed81-33a7-4a5c-8718-8d90b1de87f7",
            "cargo_categories": [
                "Non-hazardous"
            ],
            "delay_cost": null,
            "transportation_methods": [
                "Roadway",
                "Sea",
                "Transloading"
            ]
        },
        {
            "EAT": "2017-05-09 06:35:00",
            "LDT": "2017-05-10 18:35:00",
            "source": "Berth 32",
            "name": "MSC MARINA",
            "commodityGroup": "Textiles",
            "destination": "AL",
            "origin": "GUATEMALA",
            "nTEU": 2.0,
            "group_uuid": "bcf12b27-f453-4445-953e-52ee49fbe3c3",
            "cargo_categories": [
                "Non-hazardous"
            ],
            "delay_cost": null,
            "transportation_methods": [
                "Roadway",
                "Sea",
                "Transloading"
            ]
        },
        {
            "EAT": "2017-05-09 06:35:00",
            "LDT": "2017-05-10 18:35:00",
            "source": "Berth 32",
            "name": "MSC MARINA",
            "commodityGroup": "Aggregates",
            "destination": "FL",
            "origin": "BRAZIL",
            "nTEU": 52.0,
            "group_uuid": "d13f97f5-288e-466f-a0b6-946606d2518f",
            "cargo_categories": [
                "Non-hazardous"
            ],
            "delay_cost": null,
            "transportation_methods": [
                "Roadway",
                "Sea",
                "Transloading"
            ]
        },
        {
            "EAT": "2017-05-09 06:35:00",
            "LDT": "2017-05-10 18:35:00",
            "source": "Berth 32",
            "name": "MSC MARINA",
            "commodityGroup": "Furniture",
            "destination": "FL",
            "origin": "ITALY",
            "nTEU": 2.0,
            "group_uuid": "7271314e-88d2-49da-9e13-44d997a7d3ef",
            "cargo_categories": [
                "Non-hazardous"
            ],
            "delay_cost": null,
            "transportation_methods": [
                "Roadway",
                "Sea",
                "Transloading"
            ]
        },
        {
            "EAT": "2017-05-09 06:35:00",
            "LDT": "2017-05-10 18:35:00",
            "source": "Berth 32",
            "name": "MSC MARINA",
            "commodityGroup": "Furniture",
            "destination": "FL",
            "origin": "BRAZIL",
            "nTEU": 13.5,
            "group_uuid": "abe33200-94cd-4a40-8d2f-8fbc1a79ce51",
            "cargo_categories": [
                "Non-hazardous"
            ],
            "delay_cost": null,
            "transportation_methods": [
                "Roadway",
                "Sea",
                "Transloading"
            ]
        },
        {
            "EAT": "2017-05-09 06:35:00",
            "LDT": "2017-05-10 18:35:00",
            "source": "Berth 32",
            "name": "MSC MARINA",
            "commodityGroup": "Beverages",
            "destination": "FL",
            "origin": "ITALY",
            "nTEU": 1.0,
            "group_uuid": "eabc14a7-2a8e-43df-8ef8-59f5ff9b46e4",
            "cargo_categories": [
                "Non-hazardous"
            ],
            "delay_cost": null,
            "transportation_methods": [
                "Roadway",
                "Sea",
                "Transloading"
            ]
        },
        {
            "EAT": "2017-05-09 06:35:00",
            "LDT": "2017-05-10 18:35:00",
            "source": "Berth 32",
            "name": "MSC MARINA",
            "commodityGroup": "Industrial Chemicals",
            "destination": "CO",
            "origin": "HONDURAS",
            "nTEU": 1.0,
            "group_uuid": "7829707a-6f37-4dd0-b030-854129215f92",
            "cargo_categories": [
                "Non-hazardous"
            ],
            "delay_cost": null,
            "transportation_methods": [
                "Roadway",
                "Sea",
                "Transloading"
            ]
        },
        {
            "EAT": "2017-05-09 06:35:00",
            "LDT": "2017-05-10 18:35:00",
            "source": "Berth 32",
            "name": "MSC MARINA",
            "commodityGroup": "Vehicle Parts",
            "destination": "FL",
            "origin": "DOMINICAN REPUBLIC",
            "nTEU": 0.23,
            "group_uuid": "d3060574-d12b-4c3b-8680-3846842fe324",
            "cargo_categories": [
                "Non-hazardous"
            ],
            "delay_cost": null,
            "transportation_methods": [
                "Roadway",
                "Sea",
                "Transloading"
            ]
        },
        {
            "EAT": "2017-05-09 06:35:00",
            "LDT": "2017-05-10 18:35:00",
            "source": "Berth 32",
            "name": "MSC MARINA",
            "commodityGroup": "Machinery",
            "destination": "FL",
            "origin": "GUATEMALA",
            "nTEU": 3.77,
            "group_uuid": "4d246c1d-23a0-4493-82ee-48962a9f9120",
            "cargo_categories": [
                "Non-hazardous"
            ],
            "delay_cost": null,
            "transportation_methods": [
                "Roadway",
                "Sea",
                "Transloading"
            ]
        },
        {
            "EAT": "2017-05-09 06:35:00",
            "LDT": "2017-05-10 18:35:00",
            "source": "Berth 32",
            "name": "MSC MARINA",
            "commodityGroup": "All Others",
            "destination": "FL",
            "origin": "HONDURAS",
            "nTEU": 18.08,
            "group_uuid": "df9fe383-5cb1-47fc-8dc6-b56b67d5259e",
            "cargo_categories": [
                "Non-hazardous"
            ],
            "delay_cost": null,
            "transportation_methods": [
                "Roadway",
                "Sea",
                "Transloading"
            ]
        },
        {
            "EAT": "2017-05-09 06:35:00",
            "LDT": "2017-05-10 18:35:00",
            "source": "Berth 32",
            "name": "MSC MARINA",
            "commodityGroup": "Hardware/Tools",
            "destination": "FL",
            "origin": "BRAZIL",
            "nTEU": 1.0,
            "group_uuid": "12515ea0-4569-4cd5-8a7c-2f64afdde129",
            "cargo_categories": [
                "Non-hazardous"
            ],
            "delay_cost": null,
            "transportation_methods": [
                "Roadway",
                "Sea",
                "Transloading"
            ]
        },
        {
            "EAT": "2017-05-09 06:35:00",
            "LDT": "2017-05-10 18:35:00",
            "source": "Berth 32",
            "name": "MSC MARINA",
            "commodityGroup": "Soybeans",
            "destination": "FL",
            "origin": "BRAZIL",
            "nTEU": 65.0,
            "group_uuid": "159662de-3881-4278-a535-0196544978a1",
            "cargo_categories": [
                "Non-hazardous"
            ],
            "delay_cost": null,
            "transportation_methods": [
                "Roadway",
                "Sea",
                "Transloading"
            ]
        },
        {
            "EAT": "2017-05-09 06:35:00",
            "LDT": "2017-05-10 18:35:00",
            "source": "Berth 32",
            "name": "MSC MARINA",
            "commodityGroup": "Panel Products",
            "destination": "SC",
            "origin": "BRAZIL",
            "nTEU": 39.75,
            "group_uuid": "95d13497-8012-46c9-bf9d-31a74bc1091d",
            "cargo_categories": [
                "Non-hazardous"
            ],
            "delay_cost": null,
            "transportation_methods": [
                "Roadway",
                "Sea",
                "Transloading"
            ]
        },
        {
            "EAT": "2017-05-09 06:35:00",
            "LDT": "2017-05-10 18:35:00",
            "source": "Berth 32",
            "name": "MSC MARINA",
            "commodityGroup": "Household Products",
            "destination": "FL",
            "origin": "DOMINICAN REPUBLIC",
            "nTEU": 1.0,
            "group_uuid": "bb0aa777-ad8f-49be-8d8b-96dcf1d50561",
            "cargo_categories": [
                "Non-hazardous"
            ],
            "delay_cost": null,
            "transportation_methods": [
                "Roadway",
                "Sea",
                "Transloading"
            ]
        },
        {
            "EAT": "2017-05-09 06:35:00",
            "LDT": "2017-05-10 18:35:00",
            "source": "Berth 32",
            "name": "MSC MARINA",
            "commodityGroup": "Lenses",
            "destination": "NC",
            "origin": "BRAZIL",
            "nTEU": 3.5,
            "group_uuid": "b937efc0-f83f-4370-9a84-2de7a9ba711c",
            "cargo_categories": [
                "Non-hazardous"
            ],
            "delay_cost": null,
            "transportation_methods": [
                "Roadway",
                "Sea",
                "Transloading"
            ]
        },
        {
            "EAT": "2017-05-09 06:35:00",
            "LDT": "2017-05-10 18:35:00",
            "source": "Berth 32",
            "name": "MSC MARINA",
            "commodityGroup": "Glass/Ceramic",
            "destination": "FL",
            "origin": "SPAIN-S",
            "nTEU": 2.25,
            "group_uuid": "1259928d-83ba-468c-8bfa-186f033c6dbc",
            "cargo_categories": [
                "Non-hazardous"
            ],
            "delay_cost": null,
            "transportation_methods": [
                "Roadway",
                "Sea",
                "Transloading"
            ]
        }
    ]
}